dstruc_crud/__init__.py
dstruc_crud/cli.py
dstruc_crud/dstruc_crud.py
dstruc_crud-0.1.0.dist-info/AUTHORS.rst
dstruc_crud-0.1.0.dist-info/LICENSE
dstruc_crud-0.1.0.dist-info/METADATA
dstruc_crud-0.1.0.dist-info/WHEEL
dstruc_crud-0.1.0.dist-info/entry_points.txt
dstruc_crud-0.1.0.dist-info/top_level.txt
dstruc_crud-0.1.0.dist-info/RECORD
