Metadata-Version: 2.1
Name: dstruc-crud
Version: 0.1.0
Summary: This project illustrates how data structures work in Python3+ with a simple CRUD dash application.
Home-page: https://github.com/joaoheron/dstruc_crud
Author: Joao Heron
Author-email: joao@mail.com
License: Apache Software License 2.0
Keywords: dstruc_crud
Platform: UNKNOWN
Classifier: Development Status :: 2 - Pre-Alpha
Classifier: Intended Audience :: Developers
Classifier: License :: OSI Approved :: Apache Software License
Classifier: Natural Language :: English
Classifier: Programming Language :: Python :: 3
Classifier: Programming Language :: Python :: 3.5
Classifier: Programming Language :: Python :: 3.6
Classifier: Programming Language :: Python :: 3.7
Classifier: Programming Language :: Python :: 3.8
Requires-Python: >=3.5
Requires-Dist: Click (>=7.0)
